intellihub/__init__.py
intellihub/assertions.py
intellihub/core.py
intellihub/data_preprocessing.py
intellihub/dataset_types.py
intellihub/helper.py
intellihub/ml_hyperparameters.py
intellihub/visualization.py
test/__init__.py
test/ml_tests/__init__.py
test/ml_tests/test_h2o_algo_assertions.py
test/ml_tests/test_scikit_algo_assertions.py
test/ml_tests/test_weka_algo_assertions.py
intellihub-1.4.1.dist-info/LICENSE
intellihub-1.4.1.dist-info/METADATA
intellihub-1.4.1.dist-info/WHEEL
intellihub-1.4.1.dist-info/top_level.txt
intellihub-1.4.1.dist-info/RECORD
